tutork8s/__about__.py
tutork8s/__init__.py
tutork8s/plugin.py
tutork8s/patches/.gitignore
tutork8s/patches/k8s-deployments
tutork8s/patches/k8s-override
tutork8s/templates/k8s/apps/.gitignore
tutork8s/templates/k8s/build/.gitignore
tutork8s/templates/k8s/tasks/lms/.gitignore
tutor_contrib_k8s-19.1.0.dist-info/METADATA
tutor_contrib_k8s-19.1.0.dist-info/WHEEL
tutor_contrib_k8s-19.1.0.dist-info/entry_points.txt
tutor_contrib_k8s-19.1.0.dist-info/RECORD
