Metadata-Version: 2.4
Name: tutor-contrib-k8s
Version: 19.1.0
Summary: Helper plugin for Kubernetes deployments of Open edX
Project-URL: Documentation, https://github.com/aulasneo/tutor-contrib-k8s.git#readme
Project-URL: Issues, https://github.com/aulasneo/tutor-contrib-k8s.git/issues
Project-URL: Source, https://github.com/aulasneo/tutor-contrib-k8s.git
Author-email: Andrés González <andres@aulasneo.com>
License: AGPL-3.0-only
Classifier: Development Status :: 3 - Alpha
Classifier: Intended Audience :: Developers
Classifier: License :: OSI Approved :: GNU Affero General Public License v3
Classifier: Operating System :: OS Independent
Classifier: Programming Language :: Python
Classifier: Programming Language :: Python :: 3.9
Classifier: Programming Language :: Python :: 3.10
Classifier: Programming Language :: Python :: 3.11
Classifier: Programming Language :: Python :: 3.12
Classifier: Programming Language :: Python :: Implementation :: CPython
Classifier: Programming Language :: Python :: Implementation :: PyPy
Requires-Python: >=3.9
Requires-Dist: tutor<20.0.0,>=19.0.0
Provides-Extra: dev
Requires-Dist: ruff; extra == 'dev'
Requires-Dist: tutor[dev]<20.0.0,>=19.0.0; extra == 'dev'
